{"timestamp":1680654080801,"shuffle":"36:  R'   B    U    F'   L    U'   L    F'   U'  2D    U'   B   2F    U    D   2B    R    L   2F    D'   U    R'   F    U'   R'   U'   D    B'   L    U    R'   B   ","solutions":[{"label":"2x2","key":"IDDFS","solution":{"rotations":[{"side":2,"counterClockwiseDirection":true,"layer":0},{"side":2,"counterClockwiseDirection":true,"layer":0},{"side":3,"counterClockwiseDirection":true,"layer":0},{"side":0,"counterClockwiseDirection":false,"layer":0},{"side":2,"counterClockwiseDirection":true,"layer":0},{"side":2,"counterClockwiseDirection":true,"layer":0},{"side":3,"counterClockwiseDirection":true,"layer":0},{"side":2,"counterClockwiseDirection":true,"layer":0},{"side":0,"counterClockwiseDirection":true,"layer":0},{"side":0,"counterClockwiseDirection":true,"layer":0},{"side":3,"counterClockwiseDirection":true,"layer":0},{"side":3,"counterClockwiseDirection":true,"layer":0}],"totalTime":240524.1000000015,"data":{"metrics":[{"label":"PERFORM_ROTATION","totalTime":100771.90000129491,"totalRelativeTime":"41.89%","numOfCalls":72591813,"avgTimePerCall":0.0013881992450208525},{"label":"ADD_CANDIDATE","totalTime":19706.899999000132,"totalRelativeTime":"8.19%","numOfCalls":72591813,"avgTimePerCall":0.0002714755174801893},{"label":"NOT_MEASURED","totalTime":120045.29999970645,"totalRelativeTime":"49.9%","numOfCalls":0,"avgTimePerCall":120045.29999970645}],"visitedNodes":67725922,"iterations":[{"visitedNodes":37,"bound":2},{"visitedNodes":181,"bound":3},{"visitedNodes":877,"bound":4},{"visitedNodes":4237,"bound":5},{"visitedNodes":20461,"bound":6},{"visitedNodes":98797,"bound":7},{"visitedNodes":477037,"bound":8},{"visitedNodes":2303341,"bound":9},{"visitedNodes":11121517,"bound":10},{"visitedNodes":53699437,"bound":11}]}}},{"label":"2x2","key":"IDA*","solution":{"rotations":[{"side":2,"counterClockwiseDirection":true,"layer":0},{"side":2,"counterClockwiseDirection":true,"layer":0},{"side":3,"counterClockwiseDirection":true,"layer":0},{"side":0,"counterClockwiseDirection":false,"layer":0},{"side":2,"counterClockwiseDirection":true,"layer":0},{"side":2,"counterClockwiseDirection":true,"layer":0},{"side":3,"counterClockwiseDirection":true,"layer":0},{"side":2,"counterClockwiseDirection":true,"layer":0},{"side":0,"counterClockwiseDirection":true,"layer":0},{"side":0,"counterClockwiseDirection":true,"layer":0},{"side":3,"counterClockwiseDirection":true,"layer":0},{"side":3,"counterClockwiseDirection":true,"layer":0}],"totalTime":223347.5,"data":{"metrics":[{"label":"PERFORM_ROTATION","totalTime":98219.40000407398,"totalRelativeTime":"43.97%","numOfCalls":68069751,"avgTimePerCall":0.0014429228631095475},{"label":"ADD_CANDIDATE","totalTime":19186.200002647936,"totalRelativeTime":"8.59%","numOfCalls":68069751,"avgTimePerCall":0.0002818608812400083},{"label":"CYCLE_AVOIDANCE_CHECK","totalTime":4667.800000309944,"totalRelativeTime":"2.08%","numOfCalls":14098185,"avgTimePerCall":0.0003310922647354921},{"label":"NOT_MEASURED","totalTime":101274.09999296814,"totalRelativeTime":"45.34%","numOfCalls":0,"avgTimePerCall":101274.09999296814}],"visitedNodes":13024099,"iterations":[{"visitedNodes":7,"bound":2},{"visitedNodes":37,"bound":3.25},{"visitedNodes":563,"bound":4.5},{"visitedNodes":4247,"bound":5.75},{"visitedNodes":21142,"bound":7},{"visitedNodes":148189,"bound":8.25},{"visitedNodes":1701188,"bound":9.5},{"visitedNodes":11148726,"bound":10.75}]}}},{"label":"2x2","key":"GA","solution":{"rotations":[{"side":0,"counterClockwiseDirection":true,"layer":0},{"side":3,"counterClockwiseDirection":false,"layer":0},{"side":0,"counterClockwiseDirection":true,"layer":0},{"side":3,"counterClockwiseDirection":true,"layer":0},{"side":0,"counterClockwiseDirection":true,"layer":0},{"side":2,"counterClockwiseDirection":true,"layer":0},{"side":2,"counterClockwiseDirection":true,"layer":0},{"side":3,"counterClockwiseDirection":false,"layer":0},{"side":0,"counterClockwiseDirection":false,"layer":0},{"side":3,"counterClockwiseDirection":false,"layer":0},{"side":2,"counterClockwiseDirection":true,"layer":0},{"side":2,"counterClockwiseDirection":true,"layer":0},{"side":2,"counterClockwiseDirection":true,"layer":0},{"side":0,"counterClockwiseDirection":true,"layer":0},{"side":3,"counterClockwiseDirection":false,"layer":0},{"side":2,"counterClockwiseDirection":true,"layer":0},{"side":3,"counterClockwiseDirection":true,"layer":0},{"side":3,"counterClockwiseDirection":true,"layer":0},{"side":3,"counterClockwiseDirection":false,"layer":0},{"side":0,"counterClockwiseDirection":false,"layer":0},{"side":3,"counterClockwiseDirection":true,"layer":0},{"side":2,"counterClockwiseDirection":false,"layer":0},{"side":3,"counterClockwiseDirection":false,"layer":0},{"side":2,"counterClockwiseDirection":false,"layer":0},{"side":3,"counterClockwiseDirection":true,"layer":0},{"side":3,"counterClockwiseDirection":false,"layer":0},{"side":2,"counterClockwiseDirection":false,"layer":0},{"side":0,"counterClockwiseDirection":false,"layer":0}],"totalTime":43646.79999999702,"data":{"armageddonCounter":0,"generations":2797,"metrics":[{"label":"CHECK_SOLUTION","totalTime":2566.2000003382564,"totalRelativeTime":"5.87%","numOfCalls":8388840,"avgTimePerCall":0.0003059064185677944},{"label":"APPLYING_ROTATIONS","totalTime":12294.200000353158,"totalRelativeTime":"28.16%","numOfCalls":8388838,"avgTimePerCall":0.0014655426651883322},{"label":"COMPUTE_GENE","totalTime":2609.6000001057982,"totalRelativeTime":"5.97%","numOfCalls":8388838,"avgTimePerCall":0.00031108003278949934},{"label":"CALCULATE_CITIZEN_SCORE","totalTime":4623.700000837445,"totalRelativeTime":"10.59%","numOfCalls":8388838,"avgTimePerCall":0.0005511728800624646},{"label":"AGGREGATE_CURRENT_GENERATION","totalTime":87.29999984055758,"totalRelativeTime":"0.2%","numOfCalls":279627,"avgTimePerCall":0.0003122016108621756},{"label":"CREATE_NEXT_GENERATION","totalTime":353.30000004917383,"totalRelativeTime":"0.8%","numOfCalls":2796,"avgTimePerCall":0.1263590844238819},{"label":"MEASUREMENT_OVERHEAD","totalTime":10451.399999551475,"totalRelativeTime":"23.94%","numOfCalls":0,"avgTimePerCall":10451.399999551475},{"label":"NOT_MEASURED","totalTime":10661.099998921156,"totalRelativeTime":"24.42%","numOfCalls":0,"avgTimePerCall":10661.099998921156}]}}},{"label":"2x2","key":"SA","solution":{"rotations":[{"side":0,"counterClockwiseDirection":false,"layer":0},{"side":3,"counterClockwiseDirection":true,"layer":0},{"side":2,"counterClockwiseDirection":false,"layer":0},{"side":0,"counterClockwiseDirection":false,"layer":0},{"side":0,"counterClockwiseDirection":false,"layer":0},{"side":2,"counterClockwiseDirection":true,"layer":0},{"side":2,"counterClockwiseDirection":true,"layer":0},{"side":0,"counterClockwiseDirection":false,"layer":0},{"side":3,"counterClockwiseDirection":true,"layer":0},{"side":3,"counterClockwiseDirection":false,"layer":0},{"side":3,"counterClockwiseDirection":true,"layer":0},{"side":2,"counterClockwiseDirection":true,"layer":0},{"side":0,"counterClockwiseDirection":false,"layer":0},{"side":0,"counterClockwiseDirection":false,"layer":0},{"side":0,"counterClockwiseDirection":true,"layer":0},{"side":3,"counterClockwiseDirection":false,"layer":0},{"side":3,"counterClockwiseDirection":false,"layer":0},{"side":3,"counterClockwiseDirection":true,"layer":0},{"side":2,"counterClockwiseDirection":true,"layer":0},{"side":3,"counterClockwiseDirection":false,"layer":0}],"totalTime":211867.80000000447,"data":{"restartCounter":2,"iterations":14825,"metrics":[{"label":"CHECK_SOLUTION","totalTime":12144.899999886751,"totalRelativeTime":"5.73%","numOfCalls":44473200,"avgTimePerCall":0.0002730835649309416},{"label":"APPLYING_ROTATIONS","totalTime":62971.49999782443,"totalRelativeTime":"29.72%","numOfCalls":44473190,"avgTimePerCall":0.0014159429534473338},{"label":"COMPUTE_ROTATION","totalTime":12180.29999947548,"totalRelativeTime":"5.74%","numOfCalls":44473190,"avgTimePerCall":0.00027387961150246876},{"label":"CALCULATE_CITIZEN_SCORE","totalTime":23304.899999402463,"totalRelativeTime":"10.99%","numOfCalls":44473190,"avgTimePerCall":0.0005240213260933714},{"label":"AGGREGATE_CURRENT_GENERATION","totalTime":413.8999996185303,"totalRelativeTime":"0.19%","numOfCalls":1482439,"avgTimePerCall":0.00027920204448110867},{"label":"CREATE_NEXT_GENERATION","totalTime":1211.3000002130866,"totalRelativeTime":"0.57%","numOfCalls":14824,"avgTimePerCall":0.08171208851950125},{"label":"MEASUREMENT_OVERHEAD","totalTime":49509.100000962615,"totalRelativeTime":"23.36%","numOfCalls":0,"avgTimePerCall":49509.100000962615},{"label":"NOT_MEASURED","totalTime":50131.900002621114,"totalRelativeTime":"23.66%","numOfCalls":0,"avgTimePerCall":50131.900002621114}]}}},{"label":"2x2","key":"WA*","solution":{"rotations":[{"side":3,"counterClockwiseDirection":false,"layer":0},{"side":2,"counterClockwiseDirection":true,"layer":0},{"side":3,"counterClockwiseDirection":false,"layer":0},{"side":2,"counterClockwiseDirection":false,"layer":0},{"side":3,"counterClockwiseDirection":false,"layer":0},{"side":2,"counterClockwiseDirection":true,"layer":0},{"side":0,"counterClockwiseDirection":false,"layer":0},{"side":0,"counterClockwiseDirection":false,"layer":0},{"side":3,"counterClockwiseDirection":true,"layer":0},{"side":2,"counterClockwiseDirection":false,"layer":0},{"side":0,"counterClockwiseDirection":true,"layer":0},{"side":3,"counterClockwiseDirection":false,"layer":0},{"side":0,"counterClockwiseDirection":false,"layer":0},{"side":2,"counterClockwiseDirection":true,"layer":0}],"totalTime":428.59999999403954,"data":{"metrics":[{"label":"ITERATIONS_COUNTER_INCREMENT","totalTime":8.100000001490116,"totalRelativeTime":"1.88%","numOfCalls":28206,"avgTimePerCall":0.00028717294198007926},{"label":"ABORTED_VERIFICATION","totalTime":3.4999999925494194,"totalRelativeTime":"0.81%","numOfCalls":14103,"avgTimePerCall":0.00024817414681623906},{"label":"POP_CANDIDATE","totalTime":8.500000022351742,"totalRelativeTime":"1.98%","numOfCalls":14103,"avgTimePerCall":0.0006027086451359102},{"label":"VISISTED_LIST_CHECK","totalTime":26.500000052154064,"totalRelativeTime":"6.18%","numOfCalls":77091,"avgTimePerCall":0.00034374959531143797},{"label":"CHECK_SOLUTION","totalTime":4,"totalRelativeTime":"0.93%","numOfCalls":13200,"avgTimePerCall":0.00030303030303030303},{"label":"ADD_TO_VISISTED_LIST_CHECK","totalTime":3.5000000074505806,"totalRelativeTime":"0.81%","numOfCalls":13199,"avgTimePerCall":0.00026517160447386774},{"label":"PERFORM_ROTATION","totalTime":107.99999991804361,"totalRelativeTime":"25.19%","numOfCalls":62988,"avgTimePerCall":0.0017146123058049726},{"label":"HEURISTIC_CALCULATION","totalTime":37.39999996125698,"totalRelativeTime":"8.72%","numOfCalls":62988,"avgTimePerCall":0.0005937638909198098},{"label":"ADD_CANDIDATE","totalTime":23.80000003427267,"totalRelativeTime":"5.55%","numOfCalls":61775,"avgTimePerCall":0.00038526912236782956},{"label":"BUILD_SOLUTION","totalTime":0,"totalRelativeTime":"0%","numOfCalls":1,"avgTimePerCall":0},{"label":"MEASUREMENT_OVERHEAD","totalTime":90.90000001341105,"totalRelativeTime":"21.2%","numOfCalls":0,"avgTimePerCall":90.90000001341105},{"label":"NOT_MEASURED","totalTime":114.3999999910593,"totalRelativeTime":"26.69%","numOfCalls":0,"avgTimePerCall":114.3999999910593}],"visitedNodes":14103,"differentNodes":13200}}},{"label":"2x2","key":"BiBFS","solution":{"rotations":[{"side":3,"counterClockwiseDirection":false,"layer":0},{"side":0,"counterClockwiseDirection":true,"layer":0},{"side":2,"counterClockwiseDirection":true,"layer":0},{"side":0,"counterClockwiseDirection":true,"layer":0},{"side":3,"counterClockwiseDirection":false,"layer":0},{"side":0,"counterClockwiseDirection":true,"layer":0},{"side":3,"counterClockwiseDirection":false,"layer":0},{"side":3,"counterClockwiseDirection":false,"layer":0},{"side":2,"counterClockwiseDirection":false,"layer":0},{"side":3,"counterClockwiseDirection":true,"layer":0},{"side":0,"counterClockwiseDirection":true,"layer":0},{"side":3,"counterClockwiseDirection":true,"layer":0}],"totalTime":245.39999999850988,"data":{"metrics":[{"label":"POP_CANDIDATE","totalTime":3.500000014901161,"totalRelativeTime":"1.42%","numOfCalls":12186,"avgTimePerCall":0.0002872148379206599},{"label":"VISISTED_LIST_CHECK","totalTime":24.600000090897083,"totalRelativeTime":"10.02%","numOfCalls":74663,"avgTimePerCall":0.000329480466776008},{"label":"ADD_TO_VISISTED_LIST_CHECK","totalTime":3.600000001490116,"totalRelativeTime":"1.46%","numOfCalls":10600,"avgTimePerCall":0.00033962264165001094},{"label":"PERFORM_ROTATION","totalTime":98.4999999254942,"totalRelativeTime":"40.13%","numOfCalls":51876,"avgTimePerCall":0.0018987585767116623},{"label":"ADD_CANDIDATE","totalTime":13.899999931454659,"totalRelativeTime":"5.66%","numOfCalls":50812,"avgTimePerCall":0.00027355742603036014},{"label":"MEASUREMENT_OVERHEAD","totalTime":51.69999999552965,"totalRelativeTime":"21.06%","numOfCalls":0,"avgTimePerCall":51.69999999552965},{"label":"NOT_MEASURED","totalTime":49.60000003874302,"totalRelativeTime":"20.21%","numOfCalls":0,"avgTimePerCall":49.60000003874302}],"iterations":5301,"visitedNodes":5301}}}]}